{
    "$schema": "https://raw.githubusercontent.com/Azure/azure-event-hubs-emulator-installer/refs/heads/main/EventHub-Emulator/Schema/Config-schema.json",
    "UserConfig": {
      "NamespaceConfig": [
        {
          "Type": "EventHub",
          "Name": "emulatorNs1",
          "Entities": [
            {
              "Name": "sc-contracts",
              "PartitionCount": 2,
              "ConsumerGroups": [
                {
                  "Name": "Default"
                }
              ]
            },
            {
              "Name": "io-p-itn-sign-billing-01",
              "PartitionCount": 2,
              "ConsumerGroups": [
                {
                  "Name": "Default"
                }
              ]
            },
            {
              "Name": "io-p-itn-sign-analytics-01",
              "PartitionCount": 2,
              "ConsumerGroups": [
                {
                  "Name": "Default"
                }
              ]
            }
          ]
        }
      ],
      "LoggingConfig": {
        "Type": "Console"
      }
    }
  }